{
  "id": "household-csb",
  "title": "Household-CSB",
  "version": "1.0.0",
  "compatibility": {
    "minimum": "11",
    "verified": "11"
  },
  "relationships": {
    "systems": [
      {
        "id": "custom-system-builder",
        "type": "system",
        "compatibility": {}
      }
    ],
    "recommends": [
      {
        "id": "dice-so-nice",
        "type": "module",
        "compatibility": {}
      }
    ]
  },
  "authors": [
    {
      "name": "Gus"
    }
  ],
  "packs": [
    {
      "name": "actor-templates",
      "label": "Actor Templates",
      "path": "packs/actor-templates",
      "type": "Actor",
      "system": "custom-system-builder",
      "ownership": {
        "PLAYER": "OBSERVER",
        "ASSISTANT": "OWNER"
      }
    },
    {
      "name": "item-templates",
      "label": "Item Templates",
      "path": "packs/item-templates",
      "type": "Item",
      "system": "custom-system-builder",
      "ownership": {
        "PLAYER": "OBSERVER",
        "ASSISTANT": "OWNER"
      }
    },
    {
      "name": "macros",
      "label": "Macros",
      "path": "packs/macros",
      "type": "Macro",
      "system": "custom-system-builder",
      "ownership": {
        "PLAYER": "OBSERVER",
        "ASSISTANT": "OWNER"
      }
    },
    {
      "name": "rolltables",
      "label": "Rolltables",
      "path": "packs/rolltables",
      "type": "RollTable",
      "system": "custom-system-builder",
      "ownership": {
        "PLAYER": "OBSERVER",
        "ASSISTANT": "OWNER"
      }
    },
    {
      "name": "opponents",
      "label": "Opponents",
      "path": "packs/opponents",
      "type": "Actor",
      "system": "custom-system-builder",
      "ownership": {
        "PLAYER": "OBSERVER",
        "ASSISTANT": "OWNER"
      }
    },
    {
      "name": "journals",
      "label": "Journals",
      "path": "packs/journals",
      "type": "JournalEntry",
      "system": "custom-system-builder",
      "ownership": {
        "PLAYER": "OBSERVER",
        "ASSISTANT": "OWNER"
      }
    },
    {
      "name": "moves",
      "label": "Moves",
      "path": "packs/moves",
      "type": "Item",
      "system": "custom-system-builder",
      "ownership": {
        "PLAYER": "OBSERVER",
        "ASSISTANT": "OWNER"
      }
    },
    {
      "name": "traits",
      "label": "Traits",
      "path": "packs/traits",
      "type": "Item",
      "system": "custom-system-builder",
      "ownership": {
        "PLAYER": "OBSERVER",
        "ASSISTANT": "OWNER"
      }
    },
    {
      "name": "items",
      "label": "Items",
      "path": "packs/items",
      "type": "Item",
      "system": "custom-system-builder",
      "ownership": {
        "PLAYER": "OBSERVER",
        "ASSISTANT": "OWNER"
      }
    }
  ],
  "description": "Un-official module for the Household RPG from Two Little Mice. A beautiful game like this deserves a beautiful character sheet.\n\nIMPORTANT:\nThis module uses the Custom System Builder and the only thing you need to do to configure it is go to the Configuration &gt;&gt; Custom System Builder settings and add the CSS used in the correspondent field. Copy and paste the following:\n\nmodule/household-csb/styles/household.css\n\nThat's it. Save it and reload and you are ready to go."
}